async_client_library/__init__.py
async_client_library/exceptions.py
async_client_library/version.py
async_client_library/factories/__init__.py
async_client_library/factories/base.py
async_client_library-0.1b0.dist-info/METADATA
async_client_library-0.1b0.dist-info/WHEEL
async_client_library-0.1b0.dist-info/top_level.txt
async_client_library-0.1b0.dist-info/RECORD
